CiscoStyleCli/CiscoStyleCli.py
CiscoStyleCli/__init__.py
ciscostylecli-1.0.6.0.dist-info/LICENSE
ciscostylecli-1.0.6.0.dist-info/METADATA
ciscostylecli-1.0.6.0.dist-info/WHEEL
ciscostylecli-1.0.6.0.dist-info/top_level.txt
ciscostylecli-1.0.6.0.dist-info/zip-safe
ciscostylecli-1.0.6.0.dist-info/RECORD
